{
    "type": "guest",
    "username": "jackaboutboul",
    "name": "Jack Aboutboul",
    "bio": "Jack Aboutboul is a member of the Red Hat Community Architecture team and a long-time Fedora community member working closely with Fedora Marketing, Fedora Ambassadors, and is Community Manager for AlmaLinux.",
    "avatar": "/images/people/jackaboutboul.jpg",
    "avatar_small": "/images/people/jackaboutboul_small.jpg",
    "homepage": null,
    "twitter": "https://twitter.com/jackfoundation",
    "linkedin": null,
    "instagram": null,
    "gplus": null,
    "youtube": null
}